{
  "gameDetails": {
    "round": 100,
    "maxRounds": 400,
    "mapWidth": 16,
    "mapHeight": 8,
    "roundIncomeEnergy": 5,
    "buildingPrices": {
      "ATTACK": 30,
      "DEFENSE": 30,
      "ENERGY": 20,
      "TESLA": 300
    },
    "buildingsStats": {
      "ATTACK": {
        "health": 5,
        "constructionTime": 1,
        "price": 30,
        "weaponDamage": 5,
        "weaponSpeed": 2,
        "weaponCooldownPeriod": 3,
        "energyGeneratedPerTurn": 0,
        "destroyMultiplier": 1,
        "constructionScore": 4
      },
      "DEFENSE": {
        "health": 20,
        "constructionTime": 3,
        "price": 30,
        "weaponDamage": 0,
        "weaponSpeed": 0,
        "weaponCooldownPeriod": 0,
        "energyGeneratedPerTurn": 0,
        "destroyMultiplier": 1,
        "constructionScore": 10
      },
      "ENERGY": {
        "health": 5,
        "constructionTime": 1,
        "price": 20,
        "weaponDamage": 0,
        "weaponSpeed": 0,
        "weaponCooldownPeriod": 0,
        "energyGeneratedPerTurn": 3,
        "destroyMultiplier": 1,
        "constructionScore": 3
      },
      "TESLA": {
        "health": 5,
        "constructionTime": 10,
        "price": 300,
        "weaponDamage": 20,
        "weaponSpeed": 0,
        "weaponCooldownPeriod": 10,
        "energyGeneratedPerTurn": 0,
        "destroyMultiplier": 10,
        "constructionScore": 20
      }
    },
    "ironCurtainStats": {
      "activeRounds": 6,
      "resetPeriod": 50,
      "price": 150,
      "constructionScore": 20
    }
  },
  "players": [
    {
      "playerType": "A",
      "energy": 4077,
      "health": 100,
      "hitsTaken": 0,
      "score": 7247,
      "ironCurtainAvailable": false,
      "activeIronCurtainLifetime": 3,
      "isIronCurtainActive": true
    },
    {
      "playerType": "B",
      "energy": 305,
      "health": 100,
      "hitsTaken": 0,
      "score": 760,
      "ironCurtainAvailable": true,
      "activeIronCurtainLifetime": -50,
      "isIronCurtainActive": false
    }
  ],
  "gameMap": [
    [
      {
        "x": 0,
        "y": 0,
        "buildings": [
          {
            "health": 5,
            "constructionTimeLeft": -64,
            "price": 20,
            "weaponDamage": 0,
            "weaponSpeed": 0,
            "weaponCooldownTimeLeft": 0,
            "weaponCooldownPeriod": 0,
            "destroyMultiplier": 1,
            "constructionScore": 3,
            "energyGeneratedPerTurn": 3,
            "maxRange": 0,
            "buildingType": "ENERGY",
            "energyPerShot": 0,
            "x": 0,
            "y": 0,
            "playerType": "A"
          }
        ],
        "missiles": [],
        "cellOwner": "A"
      },
      {
        "x": 1,
        "y": 0,
        "buildings": [],
        "missiles": [],
        "cellOwner": "A"
      },
      {
        "x": 2,
        "y": 0,
        "buildings": [
          {
            "health": 5,
            "constructionTimeLeft": -83,
            "price": 20,
            "weaponDamage": 0,
            "weaponSpeed": 0,
            "weaponCooldownTimeLeft": 0,
            "weaponCooldownPeriod": 0,
            "destroyMultiplier": 1,
            "constructionScore": 3,
            "energyGeneratedPerTurn": 3,
            "maxRange": 0,
            "buildingType": "ENERGY",
            "energyPerShot": 0,
            "x": 2,
            "y": 0,
            "playerType": "A"
          }
        ],
        "missiles": [],
        "cellOwner": "A"
      },
      {
        "x": 3,
        "y": 0,
        "buildings": [
          {
            "health": 5,
            "constructionTimeLeft": -70,
            "price": 20,
            "weaponDamage": 0,
            "weaponSpeed": 0,
            "weaponCooldownTimeLeft": 0,
            "weaponCooldownPeriod": 0,
            "destroyMultiplier": 1,
            "constructionScore": 3,
            "energyGeneratedPerTurn": 3,
            "maxRange": 0,
            "buildingType": "ENERGY",
            "energyPerShot": 0,
            "x": 3,
            "y": 0,
            "playerType": "A"
          }
        ],
        "missiles": [],
        "cellOwner": "A"
      },
      {
        "x": 4,
        "y": 0,
        "buildings": [
          {
            "health": 5,
            "constructionTimeLeft": -65,
            "price": 20,
            "weaponDamage": 0,
            "weaponSpeed": 0,
            "weaponCooldownTimeLeft": 0,
            "weaponCooldownPeriod": 0,
            "destroyMultiplier": 1,
            "constructionScore": 3,
            "energyGeneratedPerTurn": 3,
            "maxRange": 0,
            "buildingType": "ENERGY",
            "energyPerShot": 0,
            "x": 4,
            "y": 0,
            "playerType": "A"
          }
        ],
        "missiles": [],
        "cellOwner": "A"
      },
      {
        "x": 5,
        "y": 0,
        "buildings": [
          {
            "health": 5,
            "constructionTimeLeft": -62,
            "price": 20,
            "weaponDamage": 0,
            "weaponSpeed": 0,
            "weaponCooldownTimeLeft": 0,
            "weaponCooldownPeriod": 0,
            "destroyMultiplier": 1,
            "constructionScore": 3,
            "energyGeneratedPerTurn": 3,
            "maxRange": 0,
            "buildingType": "ENERGY",
            "energyPerShot": 0,
            "x": 5,
            "y": 0,
            "playerType": "A"
          }
        ],
        "missiles": [],
        "cellOwner": "A"
      },
      {
        "x": 6,
        "y": 0,
        "buildings": [
          {
            "health": 5,
            "constructionTimeLeft": -50,
            "price": 300,
            "weaponDamage": 20,
            "weaponSpeed": 0,
            "weaponCooldownTimeLeft": 5,
            "weaponCooldownPeriod": 10,
            "destroyMultiplier": 10,
            "constructionScore": 20,
            "energyGeneratedPerTurn": 0,
            "maxRange": 9,
            "buildingType": "TESLA",
            "energyPerShot": 100,
            "x": 6,
            "y": 0,
            "playerType": "A"
          }
        ],
        "missiles": [],
        "cellOwner": "A"
      },
      {
        "x": 7,
        "y": 0,
        "buildings": [
          {
            "health": 10,
            "constructionTimeLeft": -84,
            "price": 30,
            "weaponDamage": 0,
            "weaponSpeed": 0,
            "weaponCooldownTimeLeft": 0,
            "weaponCooldownPeriod": 0,
            "destroyMultiplier": 1,
            "constructionScore": 10,
            "energyGeneratedPerTurn": 0,
            "maxRange": 0,
            "buildingType": "DEFENSE",
            "energyPerShot": 0,
            "x": 7,
            "y": 0,
            "playerType": "A"
          }
        ],
        "missiles": [],
        "cellOwner": "A"
      },
      {
        "x": 8,
        "y": 0,
        "buildings": [],
        "missiles": [],
        "cellOwner": "B"
      },
      {
        "x": 9,
        "y": 0,
        "buildings": [],
        "missiles": [],
        "cellOwner": "B"
      },
      {
        "x": 10,
        "y": 0,
        "buildings": [],
        "missiles": [],
        "cellOwner": "B"
      },
      {
        "x": 11,
        "y": 0,
        "buildings": [],
        "missiles": [],
        "cellOwner": "B"
      },
      {
        "x": 12,
        "y": 0,
        "buildings": [],
        "missiles": [],
        "cellOwner": "B"
      },
      {
        "x": 13,
        "y": 0,
        "buildings": [],
        "missiles": [],
        "cellOwner": "B"
      },
      {
        "x": 14,
        "y": 0,
        "buildings": [],
        "missiles": [],
        "cellOwner": "B"
      },
      {
        "x": 15,
        "y": 0,
        "buildings": [],
        "missiles": [],
        "cellOwner": "B"
      }
    ],
    [
      {
        "x": 0,
        "y": 1,
        "buildings": [
          {
            "health": 5,
            "constructionTimeLeft": -23,
            "price": 20,
            "weaponDamage": 0,
            "weaponSpeed": 0,
            "weaponCooldownTimeLeft": 0,
            "weaponCooldownPeriod": 0,
            "destroyMultiplier": 1,
            "constructionScore": 3,
            "energyGeneratedPerTurn": 3,
            "maxRange": 0,
            "buildingType": "ENERGY",
            "energyPerShot": 0,
            "x": 0,
            "y": 1,
            "playerType": "A"
          }
        ],
        "missiles": [],
        "cellOwner": "A"
      },
      {
        "x": 1,
        "y": 1,
        "buildings": [
          {
            "health": 5,
            "constructionTimeLeft": -67,
            "price": 20,
            "weaponDamage": 0,
            "weaponSpeed": 0,
            "weaponCooldownTimeLeft": 0,
            "weaponCooldownPeriod": 0,
            "destroyMultiplier": 1,
            "constructionScore": 3,
            "energyGeneratedPerTurn": 3,
            "maxRange": 0,
            "buildingType": "ENERGY",
            "energyPerShot": 0,
            "x": 1,
            "y": 1,
            "playerType": "A"
          }
        ],
        "missiles": [],
        "cellOwner": "A"
      },
      {
        "x": 2,
        "y": 1,
        "buildings": [
          {
            "health": 5,
            "constructionTimeLeft": -91,
            "price": 20,
            "weaponDamage": 0,
            "weaponSpeed": 0,
            "weaponCooldownTimeLeft": 0,
            "weaponCooldownPeriod": 0,
            "destroyMultiplier": 1,
            "constructionScore": 3,
            "energyGeneratedPerTurn": 3,
            "maxRange": 0,
            "buildingType": "ENERGY",
            "energyPerShot": 0,
            "x": 2,
            "y": 1,
            "playerType": "A"
          }
        ],
        "missiles": [],
        "cellOwner": "A"
      },
      {
        "x": 3,
        "y": 1,
        "buildings": [
          {
            "health": 5,
            "constructionTimeLeft": -5,
            "price": 20,
            "weaponDamage": 0,
            "weaponSpeed": 0,
            "weaponCooldownTimeLeft": 0,
            "weaponCooldownPeriod": 0,
            "destroyMultiplier": 1,
            "constructionScore": 3,
            "energyGeneratedPerTurn": 3,
            "maxRange": 0,
            "buildingType": "ENERGY",
            "energyPerShot": 0,
            "x": 3,
            "y": 1,
            "playerType": "A"
          }
        ],
        "missiles": [],
        "cellOwner": "A"
      },
      {
        "x": 4,
        "y": 1,
        "buildings": [
          {
            "health": 5,
            "constructionTimeLeft": -97,
            "price": 20,
            "weaponDamage": 0,
            "weaponSpeed": 0,
            "weaponCooldownTimeLeft": 0,
            "weaponCooldownPeriod": 0,
            "destroyMultiplier": 1,
            "constructionScore": 3,
            "energyGeneratedPerTurn": 3,
            "maxRange": 0,
            "buildingType": "ENERGY",
            "energyPerShot": 0,
            "x": 4,
            "y": 1,
            "playerType": "A"
          }
        ],
        "missiles": [],
        "cellOwner": "A"
      },
      {
        "x": 5,
        "y": 1,
        "buildings": [
          {
            "health": 5,
            "constructionTimeLeft": -32,
            "price": 20,
            "weaponDamage": 0,
            "weaponSpeed": 0,
            "weaponCooldownTimeLeft": 0,
            "weaponCooldownPeriod": 0,
            "destroyMultiplier": 1,
            "constructionScore": 3,
            "energyGeneratedPerTurn": 3,
            "maxRange": 0,
            "buildingType": "ENERGY",
            "energyPerShot": 0,
            "x": 5,
            "y": 1,
            "playerType": "A"
          }
        ],
        "missiles": [],
        "cellOwner": "A"
      },
      {
        "x": 6,
        "y": 1,
        "buildings": [],
        "missiles": [],
        "cellOwner": "A"
      },
      {
        "x": 7,
        "y": 1,
        "buildings": [
          {
            "health": 20,
            "constructionTimeLeft": -82,
            "price": 30,
            "weaponDamage": 0,
            "weaponSpeed": 0,
            "weaponCooldownTimeLeft": 0,
            "weaponCooldownPeriod": 0,
            "destroyMultiplier": 1,
            "constructionScore": 10,
            "energyGeneratedPerTurn": 0,
            "maxRange": 0,
            "buildingType": "DEFENSE",
            "energyPerShot": 0,
            "x": 7,
            "y": 1,
            "playerType": "A"
          }
        ],
        "missiles": [],
        "cellOwner": "A"
      },
      {
        "x": 8,
        "y": 1,
        "buildings": [],
        "missiles": [],
        "cellOwner": "B"
      },
      {
        "x": 9,
        "y": 1,
        "buildings": [],
        "missiles": [],
        "cellOwner": "B"
      },
      {
        "x": 10,
        "y": 1,
        "buildings": [],
        "missiles": [],
        "cellOwner": "B"
      },
      {
        "x": 11,
        "y": 1,
        "buildings": [],
        "missiles": [],
        "cellOwner": "B"
      },
      {
        "x": 12,
        "y": 1,
        "buildings": [],
        "missiles": [],
        "cellOwner": "B"
      },
      {
        "x": 13,
        "y": 1,
        "buildings": [],
        "missiles": [],
        "cellOwner": "B"
      },
      {
        "x": 14,
        "y": 1,
        "buildings": [],
        "missiles": [],
        "cellOwner": "B"
      },
      {
        "x": 15,
        "y": 1,
        "buildings": [],
        "missiles": [],
        "cellOwner": "B"
      }
    ],
    [
      {
        "x": 0,
        "y": 2,
        "buildings": [],
        "missiles": [],
        "cellOwner": "A"
      },
      {
        "x": 1,
        "y": 2,
        "buildings": [
          {
            "health": 5,
            "constructionTimeLeft": -93,
            "price": 20,
            "weaponDamage": 0,
            "weaponSpeed": 0,
            "weaponCooldownTimeLeft": 0,
            "weaponCooldownPeriod": 0,
            "destroyMultiplier": 1,
            "constructionScore": 3,
            "energyGeneratedPerTurn": 3,
            "maxRange": 0,
            "buildingType": "ENERGY",
            "energyPerShot": 0,
            "x": 1,
            "y": 2,
            "playerType": "A"
          }
        ],
        "missiles": [],
        "cellOwner": "A"
      },
      {
        "x": 2,
        "y": 2,
        "buildings": [],
        "missiles": [],
        "cellOwner": "A"
      },
      {
        "x": 3,
        "y": 2,
        "buildings": [
          {
            "health": 5,
            "constructionTimeLeft": -10,
            "price": 20,
            "weaponDamage": 0,
            "weaponSpeed": 0,
            "weaponCooldownTimeLeft": 0,
            "weaponCooldownPeriod": 0,
            "destroyMultiplier": 1,
            "constructionScore": 3,
            "energyGeneratedPerTurn": 3,
            "maxRange": 0,
            "buildingType": "ENERGY",
            "energyPerShot": 0,
            "x": 3,
            "y": 2,
            "playerType": "A"
          }
        ],
        "missiles": [],
        "cellOwner": "A"
      },
      {
        "x": 4,
        "y": 2,
        "buildings": [
          {
            "health": 5,
            "constructionTimeLeft": -71,
            "price": 20,
            "weaponDamage": 0,
            "weaponSpeed": 0,
            "weaponCooldownTimeLeft": 0,
            "weaponCooldownPeriod": 0,
            "destroyMultiplier": 1,
            "constructionScore": 3,
            "energyGeneratedPerTurn": 3,
            "maxRange": 0,
            "buildingType": "ENERGY",
            "energyPerShot": 0,
            "x": 4,
            "y": 2,
            "playerType": "A"
          }
        ],
        "missiles": [],
        "cellOwner": "A"
      },
      {
        "x": 5,
        "y": 2,
        "buildings": [
          {
            "health": 5,
            "constructionTimeLeft": -40,
            "price": 20,
            "weaponDamage": 0,
            "weaponSpeed": 0,
            "weaponCooldownTimeLeft": 0,
            "weaponCooldownPeriod": 0,
            "destroyMultiplier": 1,
            "constructionScore": 3,
            "energyGeneratedPerTurn": 3,
            "maxRange": 0,
            "buildingType": "ENERGY",
            "energyPerShot": 0,
            "x": 5,
            "y": 2,
            "playerType": "A"
          }
        ],
        "missiles": [],
        "cellOwner": "A"
      },
      {
        "x": 6,
        "y": 2,
        "buildings": [],
        "missiles": [],
        "cellOwner": "A"
      },
      {
        "x": 7,
        "y": 2,
        "buildings": [
          {
            "health": 20,
            "constructionTimeLeft": -79,
            "price": 30,
            "weaponDamage": 0,
            "weaponSpeed": 0,
            "weaponCooldownTimeLeft": 0,
            "weaponCooldownPeriod": 0,
            "destroyMultiplier": 1,
            "constructionScore": 10,
            "energyGeneratedPerTurn": 0,
            "maxRange": 0,
            "buildingType": "DEFENSE",
            "energyPerShot": 0,
            "x": 7,
            "y": 2,
            "playerType": "A"
          }
        ],
        "missiles": [],
        "cellOwner": "A"
      },
      {
        "x": 8,
        "y": 2,
        "buildings": [],
        "missiles": [],
        "cellOwner": "B"
      },
      {
        "x": 9,
        "y": 2,
        "buildings": [],
        "missiles": [],
        "cellOwner": "B"
      },
      {
        "x": 10,
        "y": 2,
        "buildings": [],
        "missiles": [],
        "cellOwner": "B"
      },
      {
        "x": 11,
        "y": 2,
        "buildings": [],
        "missiles": [],
        "cellOwner": "B"
      },
      {
        "x": 12,
        "y": 2,
        "buildings": [],
        "missiles": [],
        "cellOwner": "B"
      },
      {
        "x": 13,
        "y": 2,
        "buildings": [],
        "missiles": [],
        "cellOwner": "B"
      },
      {
        "x": 14,
        "y": 2,
        "buildings": [],
        "missiles": [],
        "cellOwner": "B"
      },
      {
        "x": 15,
        "y": 2,
        "buildings": [
          {
            "health": 20,
            "constructionTimeLeft": -1,
            "price": 30,
            "weaponDamage": 0,
            "weaponSpeed": 0,
            "weaponCooldownTimeLeft": 0,
            "weaponCooldownPeriod": 0,
            "destroyMultiplier": 1,
            "constructionScore": 10,
            "energyGeneratedPerTurn": 0,
            "maxRange": 0,
            "buildingType": "DEFENSE",
            "energyPerShot": 0,
            "x": 15,
            "y": 2,
            "playerType": "B"
          }
        ],
        "missiles": [],
        "cellOwner": "B"
      }
    ],
    [
      {
        "x": 0,
        "y": 3,
        "buildings": [
          {
            "health": 5,
            "constructionTimeLeft": -4,
            "price": 20,
            "weaponDamage": 0,
            "weaponSpeed": 0,
            "weaponCooldownTimeLeft": 0,
            "weaponCooldownPeriod": 0,
            "destroyMultiplier": 1,
            "constructionScore": 3,
            "energyGeneratedPerTurn": 3,
            "maxRange": 0,
            "buildingType": "ENERGY",
            "energyPerShot": 0,
            "x": 0,
            "y": 3,
            "playerType": "A"
          }
        ],
        "missiles": [],
        "cellOwner": "A"
      },
      {
        "x": 1,
        "y": 3,
        "buildings": [
          {
            "health": 5,
            "constructionTimeLeft": -14,
            "price": 20,
            "weaponDamage": 0,
            "weaponSpeed": 0,
            "weaponCooldownTimeLeft": 0,
            "weaponCooldownPeriod": 0,
            "destroyMultiplier": 1,
            "constructionScore": 3,
            "energyGeneratedPerTurn": 3,
            "maxRange": 0,
            "buildingType": "ENERGY",
            "energyPerShot": 0,
            "x": 1,
            "y": 3,
            "playerType": "A"
          }
        ],
        "missiles": [],
        "cellOwner": "A"
      },
      {
        "x": 2,
        "y": 3,
        "buildings": [
          {
            "health": 5,
            "constructionTimeLeft": -90,
            "price": 20,
            "weaponDamage": 0,
            "weaponSpeed": 0,
            "weaponCooldownTimeLeft": 0,
            "weaponCooldownPeriod": 0,
            "destroyMultiplier": 1,
            "constructionScore": 3,
            "energyGeneratedPerTurn": 3,
            "maxRange": 0,
            "buildingType": "ENERGY",
            "energyPerShot": 0,
            "x": 2,
            "y": 3,
            "playerType": "A"
          }
        ],
        "missiles": [],
        "cellOwner": "A"
      },
      {
        "x": 3,
        "y": 3,
        "buildings": [
          {
            "health": 5,
            "constructionTimeLeft": -87,
            "price": 20,
            "weaponDamage": 0,
            "weaponSpeed": 0,
            "weaponCooldownTimeLeft": 0,
            "weaponCooldownPeriod": 0,
            "destroyMultiplier": 1,
            "constructionScore": 3,
            "energyGeneratedPerTurn": 3,
            "maxRange": 0,
            "buildingType": "ENERGY",
            "energyPerShot": 0,
            "x": 3,
            "y": 3,
            "playerType": "A"
          }
        ],
        "missiles": [],
        "cellOwner": "A"
      },
      {
        "x": 4,
        "y": 3,
        "buildings": [
          {
            "health": 5,
            "constructionTimeLeft": -58,
            "price": 20,
            "weaponDamage": 0,
            "weaponSpeed": 0,
            "weaponCooldownTimeLeft": 0,
            "weaponCooldownPeriod": 0,
            "destroyMultiplier": 1,
            "constructionScore": 3,
            "energyGeneratedPerTurn": 3,
            "maxRange": 0,
            "buildingType": "ENERGY",
            "energyPerShot": 0,
            "x": 4,
            "y": 3,
            "playerType": "A"
          }
        ],
        "missiles": [],
        "cellOwner": "A"
      },
      {
        "x": 5,
        "y": 3,
        "buildings": [
          {
            "health": 5,
            "constructionTimeLeft": -13,
            "price": 20,
            "weaponDamage": 0,
            "weaponSpeed": 0,
            "weaponCooldownTimeLeft": 0,
            "weaponCooldownPeriod": 0,
            "destroyMultiplier": 1,
            "constructionScore": 3,
            "energyGeneratedPerTurn": 3,
            "maxRange": 0,
            "buildingType": "ENERGY",
            "energyPerShot": 0,
            "x": 5,
            "y": 3,
            "playerType": "A"
          }
        ],
        "missiles": [],
        "cellOwner": "A"
      },
      {
        "x": 6,
        "y": 3,
        "buildings": [
          {
            "health": 5,
            "constructionTimeLeft": -47,
            "price": 300,
            "weaponDamage": 20,
            "weaponSpeed": 0,
            "weaponCooldownTimeLeft": 8,
            "weaponCooldownPeriod": 10,
            "destroyMultiplier": 10,
            "constructionScore": 20,
            "energyGeneratedPerTurn": 0,
            "maxRange": 9,
            "buildingType": "TESLA",
            "energyPerShot": 100,
            "x": 6,
            "y": 3,
            "playerType": "A"
          }
        ],
        "missiles": [],
        "cellOwner": "A"
      },
      {
        "x": 7,
        "y": 3,
        "buildings": [
          {
            "health": 20,
            "constructionTimeLeft": -78,
            "price": 30,
            "weaponDamage": 0,
            "weaponSpeed": 0,
            "weaponCooldownTimeLeft": 0,
            "weaponCooldownPeriod": 0,
            "destroyMultiplier": 1,
            "constructionScore": 10,
            "energyGeneratedPerTurn": 0,
            "maxRange": 0,
            "buildingType": "DEFENSE",
            "energyPerShot": 0,
            "x": 7,
            "y": 3,
            "playerType": "A"
          }
        ],
        "missiles": [],
        "cellOwner": "A"
      },
      {
        "x": 8,
        "y": 3,
        "buildings": [],
        "missiles": [],
        "cellOwner": "B"
      },
      {
        "x": 9,
        "y": 3,
        "buildings": [],
        "missiles": [],
        "cellOwner": "B"
      },
      {
        "x": 10,
        "y": 3,
        "buildings": [],
        "missiles": [],
        "cellOwner": "B"
      },
      {
        "x": 11,
        "y": 3,
        "buildings": [],
        "missiles": [],
        "cellOwner": "B"
      },
      {
        "x": 12,
        "y": 3,
        "buildings": [],
        "missiles": [],
        "cellOwner": "B"
      },
      {
        "x": 13,
        "y": 3,
        "buildings": [],
        "missiles": [],
        "cellOwner": "B"
      },
      {
        "x": 14,
        "y": 3,
        "buildings": [],
        "missiles": [],
        "cellOwner": "B"
      },
      {
        "x": 15,
        "y": 3,
        "buildings": [],
        "missiles": [],
        "cellOwner": "B"
      }
    ],
    [
      {
        "x": 0,
        "y": 4,
        "buildings": [],
        "missiles": [],
        "cellOwner": "A"
      },
      {
        "x": 1,
        "y": 4,
        "buildings": [
          {
            "health": 5,
            "constructionTimeLeft": -50,
            "price": 20,
            "weaponDamage": 0,
            "weaponSpeed": 0,
            "weaponCooldownTimeLeft": 0,
            "weaponCooldownPeriod": 0,
            "destroyMultiplier": 1,
            "constructionScore": 3,
            "energyGeneratedPerTurn": 3,
            "maxRange": 0,
            "buildingType": "ENERGY",
            "energyPerShot": 0,
            "x": 1,
            "y": 4,
            "playerType": "A"
          }
        ],
        "missiles": [],
        "cellOwner": "A"
      },
      {
        "x": 2,
        "y": 4,
        "buildings": [
          {
            "health": 5,
            "constructionTimeLeft": -52,
            "price": 20,
            "weaponDamage": 0,
            "weaponSpeed": 0,
            "weaponCooldownTimeLeft": 0,
            "weaponCooldownPeriod": 0,
            "destroyMultiplier": 1,
            "constructionScore": 3,
            "energyGeneratedPerTurn": 3,
            "maxRange": 0,
            "buildingType": "ENERGY",
            "energyPerShot": 0,
            "x": 2,
            "y": 4,
            "playerType": "A"
          }
        ],
        "missiles": [],
        "cellOwner": "A"
      },
      {
        "x": 3,
        "y": 4,
        "buildings": [
          {
            "health": 5,
            "constructionTimeLeft": -82,
            "price": 20,
            "weaponDamage": 0,
            "weaponSpeed": 0,
            "weaponCooldownTimeLeft": 0,
            "weaponCooldownPeriod": 0,
            "destroyMultiplier": 1,
            "constructionScore": 3,
            "energyGeneratedPerTurn": 3,
            "maxRange": 0,
            "buildingType": "ENERGY",
            "energyPerShot": 0,
            "x": 3,
            "y": 4,
            "playerType": "A"
          }
        ],
        "missiles": [],
        "cellOwner": "A"
      },
      {
        "x": 4,
        "y": 4,
        "buildings": [],
        "missiles": [],
        "cellOwner": "A"
      },
      {
        "x": 5,
        "y": 4,
        "buildings": [],
        "missiles": [],
        "cellOwner": "A"
      },
      {
        "x": 6,
        "y": 4,
        "buildings": [],
        "missiles": [],
        "cellOwner": "A"
      },
      {
        "x": 7,
        "y": 4,
        "buildings": [
          {
            "health": 10,
            "constructionTimeLeft": -77,
            "price": 30,
            "weaponDamage": 0,
            "weaponSpeed": 0,
            "weaponCooldownTimeLeft": 0,
            "weaponCooldownPeriod": 0,
            "destroyMultiplier": 1,
            "constructionScore": 10,
            "energyGeneratedPerTurn": 0,
            "maxRange": 0,
            "buildingType": "DEFENSE",
            "energyPerShot": 0,
            "x": 7,
            "y": 4,
            "playerType": "A"
          }
        ],
        "missiles": [],
        "cellOwner": "A"
      },
      {
        "x": 8,
        "y": 4,
        "buildings": [],
        "missiles": [],
        "cellOwner": "B"
      },
      {
        "x": 9,
        "y": 4,
        "buildings": [],
        "missiles": [],
        "cellOwner": "B"
      },
      {
        "x": 10,
        "y": 4,
        "buildings": [],
        "missiles": [],
        "cellOwner": "B"
      },
      {
        "x": 11,
        "y": 4,
        "buildings": [],
        "missiles": [],
        "cellOwner": "B"
      },
      {
        "x": 12,
        "y": 4,
        "buildings": [],
        "missiles": [],
        "cellOwner": "B"
      },
      {
        "x": 13,
        "y": 4,
        "buildings": [],
        "missiles": [],
        "cellOwner": "B"
      },
      {
        "x": 14,
        "y": 4,
        "buildings": [],
        "missiles": [],
        "cellOwner": "B"
      },
      {
        "x": 15,
        "y": 4,
        "buildings": [],
        "missiles": [],
        "cellOwner": "B"
      }
    ],
    [
      {
        "x": 0,
        "y": 5,
        "buildings": [
          {
            "health": 5,
            "constructionTimeLeft": -77,
            "price": 20,
            "weaponDamage": 0,
            "weaponSpeed": 0,
            "weaponCooldownTimeLeft": 0,
            "weaponCooldownPeriod": 0,
            "destroyMultiplier": 1,
            "constructionScore": 3,
            "energyGeneratedPerTurn": 3,
            "maxRange": 0,
            "buildingType": "ENERGY",
            "energyPerShot": 0,
            "x": 0,
            "y": 5,
            "playerType": "A"
          }
        ],
        "missiles": [],
        "cellOwner": "A"
      },
      {
        "x": 1,
        "y": 5,
        "buildings": [
          {
            "health": 5,
            "constructionTimeLeft": -46,
            "price": 20,
            "weaponDamage": 0,
            "weaponSpeed": 0,
            "weaponCooldownTimeLeft": 0,
            "weaponCooldownPeriod": 0,
            "destroyMultiplier": 1,
            "constructionScore": 3,
            "energyGeneratedPerTurn": 3,
            "maxRange": 0,
            "buildingType": "ENERGY",
            "energyPerShot": 0,
            "x": 1,
            "y": 5,
            "playerType": "A"
          }
        ],
        "missiles": [],
        "cellOwner": "A"
      },
      {
        "x": 2,
        "y": 5,
        "buildings": [
          {
            "health": 5,
            "constructionTimeLeft": -43,
            "price": 20,
            "weaponDamage": 0,
            "weaponSpeed": 0,
            "weaponCooldownTimeLeft": 0,
            "weaponCooldownPeriod": 0,
            "destroyMultiplier": 1,
            "constructionScore": 3,
            "energyGeneratedPerTurn": 3,
            "maxRange": 0,
            "buildingType": "ENERGY",
            "energyPerShot": 0,
            "x": 2,
            "y": 5,
            "playerType": "A"
          }
        ],
        "missiles": [],
        "cellOwner": "A"
      },
      {
        "x": 3,
        "y": 5,
        "buildings": [],
        "missiles": [],
        "cellOwner": "A"
      },
      {
        "x": 4,
        "y": 5,
        "buildings": [],
        "missiles": [],
        "cellOwner": "A"
      },
      {
        "x": 5,
        "y": 5,
        "buildings": [],
        "missiles": [],
        "cellOwner": "A"
      },
      {
        "x": 6,
        "y": 5,
        "buildings": [],
        "missiles": [],
        "cellOwner": "A"
      },
      {
        "x": 7,
        "y": 5,
        "buildings": [
          {
            "health": 15,
            "constructionTimeLeft": -4,
            "price": 30,
            "weaponDamage": 0,
            "weaponSpeed": 0,
            "weaponCooldownTimeLeft": 0,
            "weaponCooldownPeriod": 0,
            "destroyMultiplier": 1,
            "constructionScore": 10,
            "energyGeneratedPerTurn": 0,
            "maxRange": 0,
            "buildingType": "DEFENSE",
            "energyPerShot": 0,
            "x": 7,
            "y": 5,
            "playerType": "A"
          }
        ],
        "missiles": [],
        "cellOwner": "A"
      },
      {
        "x": 8,
        "y": 5,
        "buildings": [
          {
            "health": 20,
            "constructionTimeLeft": -20,
            "price": 30,
            "weaponDamage": 0,
            "weaponSpeed": 0,
            "weaponCooldownTimeLeft": 0,
            "weaponCooldownPeriod": 0,
            "destroyMultiplier": 1,
            "constructionScore": 10,
            "energyGeneratedPerTurn": 0,
            "maxRange": 0,
            "buildingType": "DEFENSE",
            "energyPerShot": 0,
            "x": 8,
            "y": 5,
            "playerType": "B"
          }
        ],
        "missiles": [
          {
            "damage": 5,
            "speed": 2,
            "id": "518b1386-5987-4607-9b90-774a9cdca40e",
            "x": 8,
            "y": 5,
            "playerType": "B"
          }
        ],
        "cellOwner": "B"
      },
      {
        "x": 9,
        "y": 5,
        "buildings": [
          {
            "health": 5,
            "constructionTimeLeft": -14,
            "price": 30,
            "weaponDamage": 5,
            "weaponSpeed": 2,
            "weaponCooldownTimeLeft": 2,
            "weaponCooldownPeriod": 3,
            "destroyMultiplier": 1,
            "constructionScore": 4,
            "energyGeneratedPerTurn": 0,
            "maxRange": 0,
            "buildingType": "ATTACK",
            "energyPerShot": 0,
            "x": 9,
            "y": 5,
            "playerType": "B"
          }
        ],
        "missiles": [],
        "cellOwner": "B"
      },
      {
        "x": 10,
        "y": 5,
        "buildings": [
          {
            "health": 5,
            "constructionTimeLeft": -37,
            "price": 30,
            "weaponDamage": 5,
            "weaponSpeed": 2,
            "weaponCooldownTimeLeft": 3,
            "weaponCooldownPeriod": 3,
            "destroyMultiplier": 1,
            "constructionScore": 4,
            "energyGeneratedPerTurn": 0,
            "maxRange": 0,
            "buildingType": "ATTACK",
            "energyPerShot": 0,
            "x": 10,
            "y": 5,
            "playerType": "B"
          }
        ],
        "missiles": [],
        "cellOwner": "B"
      },
      {
        "x": 11,
        "y": 5,
        "buildings": [],
        "missiles": [],
        "cellOwner": "B"
      },
      {
        "x": 12,
        "y": 5,
        "buildings": [],
        "missiles": [],
        "cellOwner": "B"
      },
      {
        "x": 13,
        "y": 5,
        "buildings": [],
        "missiles": [],
        "cellOwner": "B"
      },
      {
        "x": 14,
        "y": 5,
        "buildings": [],
        "missiles": [],
        "cellOwner": "B"
      },
      {
        "x": 15,
        "y": 5,
        "buildings": [],
        "missiles": [],
        "cellOwner": "B"
      }
    ],
    [
      {
        "x": 0,
        "y": 6,
        "buildings": [],
        "missiles": [],
        "cellOwner": "A"
      },
      {
        "x": 1,
        "y": 6,
        "buildings": [
          {
            "health": 5,
            "constructionTimeLeft": -85,
            "price": 20,
            "weaponDamage": 0,
            "weaponSpeed": 0,
            "weaponCooldownTimeLeft": 0,
            "weaponCooldownPeriod": 0,
            "destroyMultiplier": 1,
            "constructionScore": 3,
            "energyGeneratedPerTurn": 3,
            "maxRange": 0,
            "buildingType": "ENERGY",
            "energyPerShot": 0,
            "x": 1,
            "y": 6,
            "playerType": "A"
          }
        ],
        "missiles": [],
        "cellOwner": "A"
      },
      {
        "x": 2,
        "y": 6,
        "buildings": [],
        "missiles": [],
        "cellOwner": "A"
      },
      {
        "x": 3,
        "y": 6,
        "buildings": [
          {
            "health": 5,
            "constructionTimeLeft": -74,
            "price": 20,
            "weaponDamage": 0,
            "weaponSpeed": 0,
            "weaponCooldownTimeLeft": 0,
            "weaponCooldownPeriod": 0,
            "destroyMultiplier": 1,
            "constructionScore": 3,
            "energyGeneratedPerTurn": 3,
            "maxRange": 0,
            "buildingType": "ENERGY",
            "energyPerShot": 0,
            "x": 3,
            "y": 6,
            "playerType": "A"
          }
        ],
        "missiles": [],
        "cellOwner": "A"
      },
      {
        "x": 4,
        "y": 6,
        "buildings": [
          {
            "health": 5,
            "constructionTimeLeft": -95,
            "price": 20,
            "weaponDamage": 0,
            "weaponSpeed": 0,
            "weaponCooldownTimeLeft": 0,
            "weaponCooldownPeriod": 0,
            "destroyMultiplier": 1,
            "constructionScore": 3,
            "energyGeneratedPerTurn": 3,
            "maxRange": 0,
            "buildingType": "ENERGY",
            "energyPerShot": 0,
            "x": 4,
            "y": 6,
            "playerType": "A"
          }
        ],
        "missiles": [],
        "cellOwner": "A"
      },
      {
        "x": 5,
        "y": 6,
        "buildings": [],
        "missiles": [],
        "cellOwner": "A"
      },
      {
        "x": 6,
        "y": 6,
        "buildings": [],
        "missiles": [],
        "cellOwner": "A"
      },
      {
        "x": 7,
        "y": 6,
        "buildings": [
          {
            "health": 10,
            "constructionTimeLeft": -13,
            "price": 30,
            "weaponDamage": 0,
            "weaponSpeed": 0,
            "weaponCooldownTimeLeft": 0,
            "weaponCooldownPeriod": 0,
            "destroyMultiplier": 1,
            "constructionScore": 10,
            "energyGeneratedPerTurn": 0,
            "maxRange": 0,
            "buildingType": "DEFENSE",
            "energyPerShot": 0,
            "x": 7,
            "y": 6,
            "playerType": "A"
          }
        ],
        "missiles": [],
        "cellOwner": "A"
      },
      {
        "x": 8,
        "y": 6,
        "buildings": [
          {
            "health": 5,
            "constructionTimeLeft": -31,
            "price": 30,
            "weaponDamage": 5,
            "weaponSpeed": 2,
            "weaponCooldownTimeLeft": 1,
            "weaponCooldownPeriod": 3,
            "destroyMultiplier": 1,
            "constructionScore": 4,
            "energyGeneratedPerTurn": 0,
            "maxRange": 0,
            "buildingType": "ATTACK",
            "energyPerShot": 0,
            "x": 8,
            "y": 6,
            "playerType": "B"
          }
        ],
        "missiles": [],
        "cellOwner": "B"
      },
      {
        "x": 9,
        "y": 6,
        "buildings": [],
        "missiles": [],
        "cellOwner": "B"
      },
      {
        "x": 10,
        "y": 6,
        "buildings": [
          {
            "health": 20,
            "constructionTimeLeft": -5,
            "price": 30,
            "weaponDamage": 0,
            "weaponSpeed": 0,
            "weaponCooldownTimeLeft": 0,
            "weaponCooldownPeriod": 0,
            "destroyMultiplier": 1,
            "constructionScore": 10,
            "energyGeneratedPerTurn": 0,
            "maxRange": 0,
            "buildingType": "DEFENSE",
            "energyPerShot": 0,
            "x": 10,
            "y": 6,
            "playerType": "B"
          }
        ],
        "missiles": [],
        "cellOwner": "B"
      },
      {
        "x": 11,
        "y": 6,
        "buildings": [],
        "missiles": [],
        "cellOwner": "B"
      },
      {
        "x": 12,
        "y": 6,
        "buildings": [],
        "missiles": [],
        "cellOwner": "B"
      },
      {
        "x": 13,
        "y": 6,
        "buildings": [],
        "missiles": [],
        "cellOwner": "B"
      },
      {
        "x": 14,
        "y": 6,
        "buildings": [],
        "missiles": [],
        "cellOwner": "B"
      },
      {
        "x": 15,
        "y": 6,
        "buildings": [],
        "missiles": [],
        "cellOwner": "B"
      }
    ],
    [
      {
        "x": 0,
        "y": 7,
        "buildings": [
          {
            "health": 5,
            "constructionTimeLeft": -53,
            "price": 20,
            "weaponDamage": 0,
            "weaponSpeed": 0,
            "weaponCooldownTimeLeft": 0,
            "weaponCooldownPeriod": 0,
            "destroyMultiplier": 1,
            "constructionScore": 3,
            "energyGeneratedPerTurn": 3,
            "maxRange": 0,
            "buildingType": "ENERGY",
            "energyPerShot": 0,
            "x": 0,
            "y": 7,
            "playerType": "A"
          }
        ],
        "missiles": [],
        "cellOwner": "A"
      },
      {
        "x": 1,
        "y": 7,
        "buildings": [
          {
            "health": 5,
            "constructionTimeLeft": -28,
            "price": 20,
            "weaponDamage": 0,
            "weaponSpeed": 0,
            "weaponCooldownTimeLeft": 0,
            "weaponCooldownPeriod": 0,
            "destroyMultiplier": 1,
            "constructionScore": 3,
            "energyGeneratedPerTurn": 3,
            "maxRange": 0,
            "buildingType": "ENERGY",
            "energyPerShot": 0,
            "x": 1,
            "y": 7,
            "playerType": "A"
          }
        ],
        "missiles": [],
        "cellOwner": "A"
      },
      {
        "x": 2,
        "y": 7,
        "buildings": [],
        "missiles": [],
        "cellOwner": "A"
      },
      {
        "x": 3,
        "y": 7,
        "buildings": [
          {
            "health": 5,
            "constructionTimeLeft": -68,
            "price": 20,
            "weaponDamage": 0,
            "weaponSpeed": 0,
            "weaponCooldownTimeLeft": 0,
            "weaponCooldownPeriod": 0,
            "destroyMultiplier": 1,
            "constructionScore": 3,
            "energyGeneratedPerTurn": 3,
            "maxRange": 0,
            "buildingType": "ENERGY",
            "energyPerShot": 0,
            "x": 3,
            "y": 7,
            "playerType": "A"
          }
        ],
        "missiles": [],
        "cellOwner": "A"
      },
      {
        "x": 4,
        "y": 7,
        "buildings": [
          {
            "health": 5,
            "constructionTimeLeft": -88,
            "price": 20,
            "weaponDamage": 0,
            "weaponSpeed": 0,
            "weaponCooldownTimeLeft": 0,
            "weaponCooldownPeriod": 0,
            "destroyMultiplier": 1,
            "constructionScore": 3,
            "energyGeneratedPerTurn": 3,
            "maxRange": 0,
            "buildingType": "ENERGY",
            "energyPerShot": 0,
            "x": 4,
            "y": 7,
            "playerType": "A"
          }
        ],
        "missiles": [],
        "cellOwner": "A"
      },
      {
        "x": 5,
        "y": 7,
        "buildings": [
          {
            "health": 5,
            "constructionTimeLeft": -73,
            "price": 20,
            "weaponDamage": 0,
            "weaponSpeed": 0,
            "weaponCooldownTimeLeft": 0,
            "weaponCooldownPeriod": 0,
            "destroyMultiplier": 1,
            "constructionScore": 3,
            "energyGeneratedPerTurn": 3,
            "maxRange": 0,
            "buildingType": "ENERGY",
            "energyPerShot": 0,
            "x": 5,
            "y": 7,
            "playerType": "A"
          }
        ],
        "missiles": [],
        "cellOwner": "A"
      },
      {
        "x": 6,
        "y": 7,
        "buildings": [],
        "missiles": [],
        "cellOwner": "A"
      },
      {
        "x": 7,
        "y": 7,
        "buildings": [
          {
            "health": 20,
            "constructionTimeLeft": -73,
            "price": 30,
            "weaponDamage": 0,
            "weaponSpeed": 0,
            "weaponCooldownTimeLeft": 0,
            "weaponCooldownPeriod": 0,
            "destroyMultiplier": 1,
            "constructionScore": 10,
            "energyGeneratedPerTurn": 0,
            "maxRange": 0,
            "buildingType": "DEFENSE",
            "energyPerShot": 0,
            "x": 7,
            "y": 7,
            "playerType": "A"
          }
        ],
        "missiles": [],
        "cellOwner": "A"
      },
      {
        "x": 8,
        "y": 7,
        "buildings": [
          {
            "health": 5,
            "constructionTimeLeft": -25,
            "price": 20,
            "weaponDamage": 0,
            "weaponSpeed": 0,
            "weaponCooldownTimeLeft": 0,
            "weaponCooldownPeriod": 0,
            "destroyMultiplier": 1,
            "constructionScore": 3,
            "energyGeneratedPerTurn": 3,
            "maxRange": 0,
            "buildingType": "ENERGY",
            "energyPerShot": 0,
            "x": 8,
            "y": 7,
            "playerType": "B"
          }
        ],
        "missiles": [],
        "cellOwner": "B"
      },
      {
        "x": 9,
        "y": 7,
        "buildings": [],
        "missiles": [],
        "cellOwner": "B"
      },
      {
        "x": 10,
        "y": 7,
        "buildings": [],
        "missiles": [],
        "cellOwner": "B"
      },
      {
        "x": 11,
        "y": 7,
        "buildings": [],
        "missiles": [],
        "cellOwner": "B"
      },
      {
        "x": 12,
        "y": 7,
        "buildings": [],
        "missiles": [],
        "cellOwner": "B"
      },
      {
        "x": 13,
        "y": 7,
        "buildings": [],
        "missiles": [],
        "cellOwner": "B"
      },
      {
        "x": 14,
        "y": 7,
        "buildings": [],
        "missiles": [],
        "cellOwner": "B"
      },
      {
        "x": 15,
        "y": 7,
        "buildings": [],
        "missiles": [],
        "cellOwner": "B"
      }
    ]
  ],
  "teslaHitList": [],
  "ironCurtainHitList": []
}